_your_package_version.py
transformerbeemcp/__init__.py
transformerbeemcp/py.typed
transformerbeemcp/server.py
transformerbeemcp-0.0.6.dist-info/METADATA
transformerbeemcp-0.0.6.dist-info/WHEEL
transformerbeemcp-0.0.6.dist-info/entry_points.txt
transformerbeemcp-0.0.6.dist-info/RECORD
