Metadata-Version: 2.4
Name: transformerbeemcp
Version: 0.0.6
Summary: MCP server for transformer.bee
Project-URL: Changelog, https://github.com/Hochfrequenz/python_template_repository/releases
Project-URL: Homepage, https://github.com/Hochfrequenz/python_template_repository
Author-email: Hochfrequenz Unternehmensberatung GmbH <info+pip@hochfrequenz.de>
License: MIT
Keywords: bo4e,edifact,mcp,transformerbee
Classifier: Development Status :: 4 - Beta
Classifier: Environment :: Console
Classifier: Intended Audience :: Developers
Classifier: License :: OSI Approved :: MIT License
Classifier: Operating System :: OS Independent
Classifier: Programming Language :: Python
Classifier: Programming Language :: Python :: 3 :: Only
Classifier: Programming Language :: Python :: 3.11
Classifier: Programming Language :: Python :: 3.12
Classifier: Programming Language :: Python :: 3.13
Requires-Python: >=3.11
Requires-Dist: mcp[cli]
Requires-Dist: transformerbeeclient>=0.2.3
Provides-Extra: coverage
Requires-Dist: coverage==7.8.0; extra == 'coverage'
Provides-Extra: dev
Requires-Dist: pip-tools; extra == 'dev'
Requires-Dist: uv; extra == 'dev'
Provides-Extra: formatting
Requires-Dist: black==25.1.0; extra == 'formatting'
Requires-Dist: isort==6.0.1; extra == 'formatting'
Provides-Extra: linting
Requires-Dist: pylint==3.3.7; extra == 'linting'
Provides-Extra: packaging
Requires-Dist: build==1.2.2.post1; extra == 'packaging'
Requires-Dist: twine==6.1.0; extra == 'packaging'
Provides-Extra: spell-check
Requires-Dist: codespell==2.4.1; extra == 'spell-check'
Provides-Extra: tests
Requires-Dist: pytest==8.3.5; extra == 'tests'
Provides-Extra: type-check
Requires-Dist: mypy[pydantic]==1.15.0; extra == 'type-check'
